pyas2/__init__.py
pyas2/admin.py
pyas2/apps.py
pyas2/forms.py
pyas2/models.py
pyas2/settings.py
pyas2/urls.py
pyas2/utils.py
pyas2/views.py
pyas2/management/__init__.py
pyas2/management/commands/__init__.py
pyas2/management/commands/manageas2server.py
pyas2/management/commands/sendas2bulk.py
pyas2/management/commands/sendas2message.py
pyas2/migrations/0001_initial.py
pyas2/migrations/0002_auto_20190603_1329.py
pyas2/migrations/0003_auto_20221208_1310.py
pyas2/migrations/__init__.py
pyas2/templates/admin/pyas2/mdn/change_form.html
pyas2/templates/admin/pyas2/message/change_form.html
pyas2/templates/pyas2/send_as2_message.html
pyas2/templatetags/__init__.py
pyas2/templatetags/pyas2.py
pyas2/tests/__init__.py
pyas2/tests/conftest.py
pyas2/tests/test_advanced.py
pyas2/tests/test_basic.py
pyas2/tests/test_commands.py
pyas2/tests/test_views.py
pyas2/tests/fixtures/client_private.pem
pyas2/tests/fixtures/client_public.pem
pyas2/tests/fixtures/server_private.pem
pyas2/tests/fixtures/server_public.pem
pyas2/tests/fixtures/testmessage.edi
django_pyas2-1.2.3.dist-info/AUTHORS.md
django_pyas2-1.2.3.dist-info/LICENSE
django_pyas2-1.2.3.dist-info/METADATA
django_pyas2-1.2.3.dist-info/WHEEL
django_pyas2-1.2.3.dist-info/top_level.txt
django_pyas2-1.2.3.dist-info/RECORD
