Metadata-Version: 2.1
Name: django-pyas2
Version: 1.2.3
Summary: AS2 file transfer Server built on Python and Django.
Home-page: http://github.com/abhishek-ram/django-pyas2
Author: Abhishek Ram
Author-email: abhishek8816@gmail.com
License: GNU GPL v3.0
Classifier: Environment :: Web Environment
Classifier: Framework :: Django
Classifier: Intended Audience :: Developers
Classifier: License :: OSI Approved :: GNU General Public License v3 (GPLv3)
Classifier: Operating System :: OS Independent
Classifier: Programming Language :: Python
Classifier: Programming Language :: Python :: 3.7
Classifier: Programming Language :: Python :: 3.8
Classifier: Programming Language :: Python :: 3.9
Classifier: Programming Language :: Python :: 3.10
Classifier: Topic :: Security :: Cryptography
Classifier: Topic :: Communications
License-File: LICENSE
License-File: AUTHORS.md
Requires-Dist: pyas2lib (==1.4.3)
Requires-Dist: django (>=2.2.18)
Requires-Dist: requests
Provides-Extra: tests
Requires-Dist: pytest (==6.2.5) ; extra == 'tests'
Requires-Dist: pytest-cov (==2.8.1) ; extra == 'tests'
Requires-Dist: coverage (==5.0.4) ; extra == 'tests'
Requires-Dist: pytest-django (==4.5.2) ; extra == 'tests'
Requires-Dist: pytest-mock (==3.5.1) ; extra == 'tests'
Requires-Dist: pylama (==8.3.7) ; extra == 'tests'
Requires-Dist: pylint (==2.12.1) ; extra == 'tests'
Requires-Dist: pytest-black (==0.3.12) ; extra == 'tests'
Requires-Dist: black (==22.6.0) ; extra == 'tests'
Requires-Dist: django-environ (==0.4.5) ; extra == 'tests'
Requires-Dist: pyflakes (==2.4.0) ; extra == 'tests'
